{"uniform":false,"default":9.55,"lastUpdated":"2026-04","counties":[{"name":"Acadia County","rate":10.25},{"name":"Allen County","rate":11},{"name":"Ascension County","rate":9.5},{"name":"Assumption County","rate":10},{"name":"Avoyelles County","rate":9.75},{"name":"Beauregard County","rate":10},{"name":"Bienville County","rate":10},{"name":"Bossier County","rate":10},{"name":"Caddo Parish","rate":9.6},{"name":"Calcasieu County","rate":10.75},{"name":"Caldwell County","rate":11},{"name":"Cameron County","rate":5},{"name":"Catahoula County","rate":11},{"name":"Claiborne County","rate":9.63},{"name":"Concordia County","rate":10.75},{"name":"De Soto County","rate":10},{"name":"East Baton Rouge Parish","rate":10.5},{"name":"East Carroll County","rate":10},{"name":"East Feliciana County","rate":10.5},{"name":"Evangeline County","rate":11},{"name":"Franklin County","rate":10},{"name":"Grant County","rate":11},{"name":"Iberia County","rate":10.45},{"name":"Iberville County","rate":10.25},{"name":"Jackson County","rate":10},{"name":"Jefferson Davis County","rate":12},{"name":"Jefferson Parish","rate":9.75},{"name":"La Salle County","rate":9},{"name":"Lafayette County","rate":10},{"name":"Lafourche County","rate":10.35},{"name":"Lincoln County","rate":11},{"name":"Livingston County","rate":10.5},{"name":"Madison County","rate":11},{"name":"Morehouse County","rate":11},{"name":"Natchitoches County","rate":10},{"name":"Orleans County","rate":10},{"name":"Ouachita Parish","rate":10.99},{"name":"Plaquemines Parish","rate":9.75},{"name":"Pointe Coupee County","rate":10},{"name":"Rapides County","rate":10.5},{"name":"Red River County","rate":10.5},{"name":"Richland County","rate":10.25},{"name":"Sabine County","rate":10.63},{"name":"St. Bernard County","rate":10},{"name":"St. Charles County","rate":10},{"name":"St. Helena County","rate":11},{"name":"St. James County","rate":9.5},{"name":"St. John the Baptist County","rate":10.25},{"name":"St. Landry County","rate":10.55},{"name":"St. Martin County","rate":10.5},{"name":"St. Mary County","rate":10.25},{"name":"St. Tammany County","rate":9.75},{"name":"Tangipahoa County","rate":10.5},{"name":"Tensas County","rate":11.5},{"name":"Terrebonne County","rate":10.5},{"name":"Union County","rate":11},{"name":"Vermilion County","rate":11},{"name":"Vernon County","rate":10},{"name":"Washington County","rate":10.83},{"name":"Webster County","rate":10.5},{"name":"West Baton Rouge County","rate":10.25},{"name":"West Carroll County","rate":11},{"name":"West Feliciana County","rate":10},{"name":"Winn County","rate":9}],"cities":[{"name":"New Orleans","rate":10},{"name":"Baton Rouge","rate":10.5},{"name":"Shreveport","rate":9.6},{"name":"Lafayette","rate":10},{"name":"Metairie","rate":9.75},{"name":"Lake Charles","rate":10.75},{"name":"Monroe","rate":10.99},{"name":"Alexandria","rate":10.5},{"name":"Bossier City","rate":10},{"name":"Kenner","rate":9.75},{"name":"Slidell","rate":9.63},{"name":"Hammond","rate":10.5},{"name":"Houma","rate":10.5},{"name":"Covington","rate":10},{"name":"Denham Springs","rate":10.5},{"name":"Gretna","rate":9.75},{"name":"Mandeville","rate":9.75},{"name":"Natchitoches","rate":11.5},{"name":"New Iberia","rate":11},{"name":"Pineville","rate":10.5},{"name":"Ruston","rate":11},{"name":"Sulphur","rate":12.75},{"name":"Thibodaux","rate":10.35},{"name":"West Monroe","rate":11.99},{"name":"Abbeville","rate":11},{"name":"Baker","rate":11},{"name":"Bastrop","rate":11},{"name":"Belle Chasse","rate":10},{"name":"Bogalusa","rate":10.83},{"name":"Chalmette","rate":10},{"name":"Crowley","rate":11.25},{"name":"Gonzales","rate":10.5},{"name":"Harvey","rate":9.75},{"name":"La Place","rate":10.25},{"name":"Leesville","rate":10.5},{"name":"Marrero","rate":9.75},{"name":"Minden","rate":12.5},{"name":"Morgan City","rate":10.25},{"name":"Opelousas","rate":12.55},{"name":"Plaquemine","rate":10.25},{"name":"Tallulah","rate":11},{"name":"Westwego","rate":10.55},{"name":"Abita Springs","rate":9.25},{"name":"Acme","rate":9.75},{"name":"Addis","rate":10.25},{"name":"Aimwell","rate":11},{"name":"Akers","rate":8.5},{"name":"Albany","rate":10.5},{"name":"Ama","rate":10},{"name":"Amelia","rate":9.45},{"name":"Amite","rate":11},{"name":"Anacoco","rate":9.63},{"name":"Angie","rate":10.83},{"name":"Angola","rate":10},{"name":"Arabi","rate":10},{"name":"Arcadia","rate":10.5},{"name":"Archibald","rate":9.25},{"name":"Arnaudville","rate":10.55},{"name":"Ashland","rate":9},{"name":"Athens","rate":9.63},{"name":"Atlanta","rate":9},{"name":"Avery Island","rate":9.25},{"name":"Baldwin","rate":10.45},{"name":"Ball","rate":10.5},{"name":"Barataria","rate":9.75},{"name":"Barksdale Afb","rate":10},{"name":"Basile","rate":11},{"name":"Baskin","rate":10},{"name":"Batchelor","rate":9.25},{"name":"Belcher","rate":9.35},{"name":"Bell City","rate":10.75},{"name":"Belle Rose","rate":10.25},{"name":"Belmont","rate":9.63},{"name":"Bentley","rate":10},{"name":"Benton","rate":10.25},{"name":"Bernice","rate":12},{"name":"Berwick","rate":10.25},{"name":"Bethany","rate":9.35},{"name":"Bienville","rate":8},{"name":"Blanchard","rate":10.35},{"name":"Bonita","rate":11},{"name":"Boothville","rate":9.75},{"name":"Bordelonville","rate":8.25},{"name":"Bourg","rate":10.5},{"name":"Boutte","rate":10},{"name":"Boyce","rate":11},{"name":"Braithwaite","rate":10},{"name":"Branch","rate":9.25},{"name":"Breaux Bridge","rate":10.5},{"name":"Brittany","rate":9.5},{"name":"Broussard","rate":11},{"name":"Brusly","rate":10.25},{"name":"Bunkie","rate":10.55},{"name":"Buras","rate":9.75},{"name":"Burnside","rate":9.5},{"name":"Bush","rate":10.83},{"name":"Cade","rate":8.5},{"name":"Calhoun","rate":10.99},{"name":"Calvin","rate":9},{"name":"Cameron","rate":5},{"name":"Campti","rate":10.5},{"name":"Carencro","rate":11},{"name":"Carville","rate":10.92},{"name":"Castor","rate":9},{"name":"Cecilia","rate":8.5},{"name":"Center Point","rate":9.5},{"name":"Centerville","rate":9.45},{"name":"Charenton","rate":9.45},{"name":"Chase","rate":9},{"name":"Chataignier","rate":11},{"name":"Chatham","rate":10},{"name":"Chauvin","rate":10.5},{"name":"Cheneyville","rate":11},{"name":"Choudrant","rate":10.99},{"name":"Church Point","rate":10.55},{"name":"Clarence","rate":10},{"name":"Clarks","rate":10},{"name":"Clayton","rate":11},{"name":"Clinton","rate":10.5},{"name":"Cloutierville","rate":10},{"name":"Colfax","rate":11},{"name":"Collinston","rate":10.99},{"name":"Columbia","rate":11},{"name":"Convent","rate":8.5},{"name":"Converse","rate":10.63},{"name":"Cotton Valley","rate":9.25},{"name":"Cottonport","rate":10.25},{"name":"Coushatta","rate":10.5},{"name":"Creole","rate":5},{"name":"Crowville","rate":9},{"name":"Cullen","rate":10.5},{"name":"Cut Off","rate":10.4},{"name":"Darrow","rate":9.5},{"name":"Delcambre","rate":11.25},{"name":"Delhi","rate":11.25},{"name":"Delta","rate":9.5},{"name":"Dequincy","rate":10.75},{"name":"Deridder","rate":11.25},{"name":"Des Allemands","rate":10},{"name":"Destrehan","rate":10},{"name":"Deville","rate":9.5},{"name":"Dodson","rate":10},{"name":"Donaldsonville","rate":11},{"name":"Donner","rate":10.5},{"name":"Downsville","rate":10.99},{"name":"Doyline","rate":9.25},{"name":"Dry Creek","rate":9.7},{"name":"Dry Prong","rate":11},{"name":"Dubach","rate":10},{"name":"Dubberly","rate":8.5},{"name":"Dulac","rate":10.5},{"name":"Duplessis","rate":9.5},{"name":"Dupont","rate":8.25},{"name":"Duson","rate":11.25},{"name":"Echo","rate":8.5},{"name":"Edgard","rate":10.25},{"name":"Effie","rate":8.25},{"name":"Egan","rate":11.25},{"name":"Elizabeth","rate":11},{"name":"Elm Grove","rate":9.25},{"name":"Elmer","rate":8.5},{"name":"Elton","rate":12},{"name":"Empire","rate":9.75},{"name":"Enterprise","rate":11},{"name":"Epps","rate":11},{"name":"Erath","rate":11.25},{"name":"Eros","rate":10.99},{"name":"Erwinville","rate":10.25},{"name":"Estherwood","rate":9.25},{"name":"Ethel","rate":10},{"name":"Eunice","rate":11},{"name":"Evangeline","rate":9.25},{"name":"Evans","rate":9},{"name":"Evergreen","rate":8.25},{"name":"Fairbanks","rate":10.99},{"name":"Farmerville","rate":12},{"name":"Fenton","rate":10.5},{"name":"Ferriday","rate":10.75},{"name":"Fisher","rate":9.63},{"name":"Flatwoods","rate":9},{"name":"Flora","rate":9},{"name":"Florien","rate":10.63},{"name":"Fluker","rate":10},{"name":"Folsom","rate":9.75},{"name":"Fordoche","rate":10.25},{"name":"Forest","rate":11},{"name":"Forest Hill","rate":9.5},{"name":"Fort Necessity","rate":9},{"name":"Fort Polk","rate":9},{"name":"Franklin","rate":10.45},{"name":"Franklinton","rate":11.5},{"name":"French Settlement","rate":9},{"name":"Frierson","rate":9},{"name":"Galliano","rate":10.4},{"name":"Garden City","rate":9.45},{"name":"Gardner","rate":8.5},{"name":"Garyville","rate":10.25},{"name":"Geismar","rate":9.5},{"name":"Georgetown","rate":11},{"name":"Gheens","rate":9.65},{"name":"Gibsland","rate":10},{"name":"Gibson","rate":10.5},{"name":"Gilbert","rate":10},{"name":"Gilliam","rate":9.35},{"name":"Glenmora","rate":10},{"name":"Gloster","rate":9},{"name":"Glynn","rate":10.25},{"name":"Golden Meadow","rate":10.4},{"name":"Goldonna","rate":10},{"name":"Gorum","rate":9},{"name":"Grambling","rate":11.5},{"name":"Gramercy","rate":9.5},{"name":"Grand Cane","rate":10.25},{"name":"Grand Chenier","rate":5},{"name":"Grand Coteau","rate":10.55},{"name":"Grand Isle","rate":9.75},{"name":"Grant","rate":9.7},{"name":"Gray","rate":10.5},{"name":"Grayson","rate":11},{"name":"Greensburg","rate":11},{"name":"Greenwell Springs","rate":11},{"name":"Greenwood","rate":10.35},{"name":"Grosse Tete","rate":10.25},{"name":"Gueydan","rate":9.75},{"name":"Hackberry","rate":5},{"name":"Hahnville","rate":10.25},{"name":"Hall Summit","rate":10.5},{"name":"Hamburg","rate":8.25},{"name":"Harrisonburg","rate":11},{"name":"Haughton","rate":10.25},{"name":"Hayes","rate":10.75},{"name":"Haynesville","rate":10.13},{"name":"Heflin","rate":8},{"name":"Hessmer","rate":9.25},{"name":"Hester","rate":8.5},{"name":"Hineston","rate":9},{"name":"Hodge","rate":10},{"name":"Holden","rate":11},{"name":"Homer","rate":11},{"name":"Hornbeck","rate":10},{"name":"Hosston","rate":10.35},{"name":"Husser","rate":8.5},{"name":"Ida","rate":11.35},{"name":"Independence","rate":11},{"name":"Innis","rate":9.25},{"name":"Iota","rate":10.25},{"name":"Iowa","rate":19.5},{"name":"Jackson","rate":10.5},{"name":"Jamestown","rate":8},{"name":"Jarreau","rate":9.25},{"name":"Jeanerette","rate":10.45},{"name":"Jena","rate":9},{"name":"Jennings","rate":12},{"name":"Jigger","rate":9},{"name":"Jones","rate":9},{"name":"Jonesboro","rate":10},{"name":"Jonesville","rate":12},{"name":"Joyce","rate":9},{"name":"Kaplan","rate":10.75},{"name":"Keatchie","rate":10},{"name":"Keithville","rate":10},{"name":"Kelly","rate":10},{"name":"Kentwood","rate":10.83},{"name":"Kilbourne","rate":11},{"name":"Kinder","rate":12},{"name":"Kraemer","rate":9.65},{"name":"Krotz Springs","rate":10.55},{"name":"Kurthwood","rate":10.5},{"name":"Labadieville","rate":10},{"name":"Lacassine","rate":10.5},{"name":"Lacombe","rate":9.25},{"name":"Lafitte","rate":9.75},{"name":"Lake Arthur","rate":11},{"name":"Lake Providence","rate":12},{"name":"Lakeland","rate":9.25},{"name":"Larose","rate":10.4},{"name":"Lawtell","rate":10.55},{"name":"Lebeau","rate":10.55},{"name":"Leblanc","rate":9.7},{"name":"Lecompte","rate":10.5},{"name":"Lena","rate":9},{"name":"Leonville","rate":8.55},{"name":"Lettsworth","rate":10},{"name":"Libuse","rate":9.5},{"name":"Lillie","rate":11},{"name":"Lisbon","rate":8.62},{"name":"Livingston","rate":10},{"name":"Livonia","rate":10.25},{"name":"Lockport","rate":10.15},{"name":"Logansport","rate":10},{"name":"Longleaf","rate":9.5},{"name":"Longstreet","rate":9},{"name":"Longville","rate":8.75},{"name":"Loranger","rate":8.5},{"name":"Loreauville","rate":9.5},{"name":"Lottie","rate":10.25},{"name":"Luling","rate":10},{"name":"Lutcher","rate":9.5},{"name":"Lydia","rate":9.25},{"name":"Madisonville","rate":9.25},{"name":"Mamou","rate":11},{"name":"Mangham","rate":10.25},{"name":"Mansfield","rate":10.5},{"name":"Mansura","rate":10.25},{"name":"Many","rate":10.63},{"name":"Maringouin","rate":10.25},{"name":"Marion","rate":11},{"name":"Marksville","rate":11},{"name":"Marthaville","rate":9.63},{"name":"Mathews","rate":9.65},{"name":"Maurepas","rate":10},{"name":"Maurice","rate":10.75},{"name":"Melrose","rate":10},{"name":"Melville","rate":10.75},{"name":"Mer Rouge","rate":11},{"name":"Meraux","rate":10},{"name":"Mermentau","rate":9.25},{"name":"Merryville","rate":10},{"name":"Milton","rate":9},{"name":"Mittie","rate":9.7},{"name":"Montegut","rate":10.5},{"name":"Monterey","rate":11},{"name":"Montgomery","rate":10},{"name":"Mooringsport","rate":10.35},{"name":"Mora","rate":9},{"name":"Moreauville","rate":9.75},{"name":"Morganza","rate":10.25},{"name":"Morrow","rate":10.55},{"name":"Morse","rate":9.25},{"name":"Mount Airy","rate":10.25},{"name":"Mount Hermon","rate":10.83},{"name":"Napoleonville","rate":10.5},{"name":"Natalbany","rate":8.5},{"name":"Natchez","rate":10},{"name":"Negreet","rate":9.63},{"name":"New Llano","rate":10.5},{"name":"New Roads","rate":10.25},{"name":"New Sarpy","rate":10},{"name":"Newellton","rate":11.5},{"name":"Noble","rate":9.63},{"name":"Norco","rate":10},{"name":"Norwood","rate":10},{"name":"Oak Grove","rate":11.5},{"name":"Oak Ridge","rate":9.25},{"name":"Oakdale","rate":11},{"name":"Oberlin","rate":11},{"name":"Oil City","rate":10.35},{"name":"Olla","rate":11},{"name":"Oscar","rate":9.25},{"name":"Otis","rate":8.5},{"name":"Paincourtville","rate":10},{"name":"Palmetto","rate":10.55},{"name":"Paradis","rate":10},{"name":"Patterson","rate":9.45},{"name":"Paulina","rate":9.5},{"name":"Pearl River","rate":9.5},{"name":"Pelican","rate":9.63},{"name":"Perry","rate":9.25},{"name":"Pierre Part","rate":10},{"name":"Pilottown","rate":10.25},{"name":"Pine Grove","rate":10},{"name":"Pine Prairie","rate":11},{"name":"Pioneer","rate":11},{"name":"Pitkin","rate":9.7},{"name":"Plain Dealing","rate":10.25},{"name":"Plattenville","rate":10},{"name":"Plaucheville","rate":10.55},{"name":"Pleasant Hill","rate":10.63},{"name":"Pointe A La Hache","rate":9.75},{"name":"Pollock","rate":10.5},{"name":"Ponchatoula","rate":10.5},{"name":"Port Allen","rate":10.75},{"name":"Port Barre","rate":10.75},{"name":"Port Sulphur","rate":9.75},{"name":"Powhatan","rate":10},{"name":"Prairieville","rate":10.25},{"name":"Pride","rate":11},{"name":"Princeton","rate":9.25},{"name":"Provencal","rate":9.63},{"name":"Quitman","rate":10},{"name":"Raceland","rate":9.65},{"name":"Ragley","rate":10.5},{"name":"Rayne","rate":11.25},{"name":"Rayville","rate":10.75},{"name":"Reddell","rate":11},{"name":"Reeves","rate":10.7},{"name":"Reserve","rate":10.25},{"name":"Rhinehart","rate":11},{"name":"Ringgold","rate":10},{"name":"Roanoke","rate":12.5},{"name":"Robeline","rate":10.5},{"name":"Robert","rate":8.5},{"name":"Rodessa","rate":10.35},{"name":"Rosedale","rate":10.25},{"name":"Roseland","rate":11},{"name":"Rosepine","rate":10.5},{"name":"Rougon","rate":9.25},{"name":"Ruby","rate":9.5},{"name":"Saint Amant","rate":9.5},{"name":"Saint Benedict","rate":9.25},{"name":"Saint Bernard","rate":10},{"name":"Saint Francisville","rate":10.5},{"name":"Saint Gabriel","rate":10.92},{"name":"Saint James","rate":8.5},{"name":"Saint Joseph","rate":11.75},{"name":"Saint Landry","rate":11},{"name":"Saint Martinville","rate":11},{"name":"Saint Maurice","rate":9},{"name":"Saint Rose","rate":10},{"name":"Saline","rate":10},{"name":"Sarepta","rate":10.5},{"name":"Schriever","rate":10.5},{"name":"Scott","rate":11},{"name":"Shongaloo","rate":8.62},{"name":"Sibley","rate":10.5},{"name":"Sicily Island","rate":11},{"name":"Sieper","rate":9},{"name":"Sikes","rate":9},{"name":"Simmesport","rate":10.25},{"name":"Simpson","rate":9},{"name":"Simsboro","rate":10},{"name":"Singer","rate":10.75},{"name":"Slagle","rate":9},{"name":"Slaughter","rate":11},{"name":"Sondheimer","rate":10},{"name":"Sorrento","rate":9.5},{"name":"Spearsville","rate":10},{"name":"Springfield","rate":10.5},{"name":"Springhill","rate":10.5},{"name":"Starks","rate":10.75},{"name":"Start","rate":9.25},{"name":"Sterlington","rate":13.5},{"name":"Stonewall","rate":10},{"name":"Sugartown","rate":9.7},{"name":"Summerfield","rate":8.62},{"name":"Sun","rate":9.75},{"name":"Sunset","rate":12.55},{"name":"Sunshine","rate":10.92},{"name":"Swartz","rate":10.99},{"name":"Talisheek","rate":9.25},{"name":"Tangipahoa","rate":10.5},{"name":"Taylor","rate":8},{"name":"Theriot","rate":10.5},{"name":"Tickfaw","rate":10.5},{"name":"Tioga","rate":8.5},{"name":"Transylvania","rate":10},{"name":"Trout","rate":8},{"name":"Tullos","rate":9.5},{"name":"Tunica","rate":10},{"name":"Turkey Creek","rate":11},{"name":"Uncle Sam","rate":8.5},{"name":"Urania","rate":8},{"name":"Vacherie","rate":10.25},{"name":"Varnado","rate":10.83},{"name":"Venice","rate":9.75},{"name":"Ventress","rate":9.25},{"name":"Vidalia","rate":9.75},{"name":"Ville Platte","rate":11},{"name":"Vinton","rate":17.75},{"name":"Violet","rate":10},{"name":"Vivian","rate":10.35},{"name":"Wakefield","rate":10},{"name":"Walker","rate":11},{"name":"Washington","rate":11},{"name":"Waterproof","rate":11.5},{"name":"Watson","rate":10.5},{"name":"Welsh","rate":12.5},{"name":"Westlake","rate":12.75},{"name":"Weyanoke","rate":10},{"name":"White Castle","rate":10.25},{"name":"Wildsville","rate":9.75},{"name":"Wilson","rate":10},{"name":"Winnfield","rate":10.5},{"name":"Winnsboro","rate":11},{"name":"Wisner","rate":11},{"name":"Woodworth","rate":10.5},{"name":"Youngsville","rate":10.5},{"name":"Zachary","rate":11.5},{"name":"Zwolle","rate":11.63}],"zips":{"70001":{"city":"Metairie","county":"Jefferson Parish","rate":9.75},"70002":{"city":"Metairie","county":"Jefferson Parish","rate":9.75},"70003":{"city":"Metairie","county":"Jefferson Parish","rate":9.75},"70004":{"city":"Metairie","county":"Jefferson Parish","rate":9.75},"70005":{"city":"Metairie","county":"Jefferson Parish","rate":9.75},"70006":{"city":"Metairie","county":"Jefferson Parish","rate":9.75},"70009":{"city":"Metairie","county":"Jefferson Parish","rate":9.75},"70010":{"city":"Metairie","county":"Jefferson Parish","rate":9.75},"70011":{"city":"Metairie","county":"Jefferson Parish","rate":9.75},"70030":{"city":"Des Allemands","county":"St. Charles County","rate":10},"70031":{"city":"Ama","county":"St. Charles County","rate":10},"70032":{"city":"Arabi","county":"St. Bernard County","rate":10},"70033":{"city":"Metairie","county":"Jefferson Parish","rate":9.75},"70036":{"city":"Barataria","county":"Jefferson Parish","rate":9.75},"70037":{"city":"Belle Chasse","county":"Plaquemines Parish","rate":10},"70038":{"city":"Boothville","county":"Plaquemines Parish","rate":9.75},"70039":{"city":"Boutte","county":"St. Charles County","rate":10},"70040":{"city":"Braithwaite","county":"Plaquemines Parish","rate":10},"70041":{"city":"Buras","county":"Plaquemines Parish","rate":9.75},"70043":{"city":"Chalmette","county":"St. Bernard County","rate":10},"70044":{"city":"Chalmette","county":"St. Bernard County","rate":10},"70047":{"city":"Destrehan","county":"St. Charles County","rate":10},"70049":{"city":"Edgard","county":"St. John the Baptist County","rate":10.25},"70050":{"city":"Empire","county":"Plaquemines Parish","rate":9.75},"70051":{"city":"Garyville","county":"St. John the Baptist County","rate":10.25},"70052":{"city":"Gramercy","county":"St. James County","rate":9.5},"70053":{"city":"Gretna","county":"Jefferson Parish","rate":10},"70054":{"city":"Gretna","county":"Jefferson Parish","rate":9.75},"70055":{"city":"Metairie","county":"Jefferson Parish","rate":9.75},"70056":{"city":"Gretna","county":"Jefferson Parish","rate":9.75},"70057":{"city":"Hahnville","county":"St. Charles County","rate":10.25},"70058":{"city":"Harvey","county":"Jefferson Parish","rate":9.75},"70059":{"city":"Harvey","county":"Jefferson Parish","rate":9.75},"70060":{"city":"Metairie","county":"Jefferson Parish","rate":9.75},"70062":{"city":"Kenner","county":"Jefferson Parish","rate":11.75},"70063":{"city":"Kenner","county":"Jefferson Parish","rate":9.75},"70064":{"city":"Kenner","county":"Jefferson Parish","rate":9.75},"70065":{"city":"Kenner","county":"Jefferson Parish","rate":9.75},"70067":{"city":"Lafitte","county":"Jefferson Parish","rate":9.75},"70068":{"city":"La Place","county":"St. John the Baptist County","rate":10.25},"70069":{"city":"La Place","county":"St. John the Baptist County","rate":10.25},"70070":{"city":"Luling","county":"St. Charles County","rate":10},"70071":{"city":"Lutcher","county":"St. James County","rate":9.5},"70072":{"city":"Marrero","county":"Jefferson Parish","rate":9.75},"70073":{"city":"Marrero","county":"Jefferson Parish","rate":9.75},"70075":{"city":"Meraux","county":"St. Bernard County","rate":10},"70076":{"city":"Mount Airy","county":"St. John the Baptist County","rate":10.25},"70078":{"city":"New Sarpy","county":"St. Charles County","rate":10},"70079":{"city":"Norco","county":"St. Charles County","rate":10},"70080":{"city":"Paradis","county":"St. Charles County","rate":10},"70081":{"city":"Pilottown","county":"Plaquemines Parish","rate":10.25},"70082":{"city":"Pointe A La Hache","county":"Plaquemines Parish","rate":9.75},"70083":{"city":"Port Sulphur","county":"Plaquemines Parish","rate":9.75},"70084":{"city":"Reserve","county":"St. John the Baptist County","rate":10.25},"70085":{"city":"Saint Bernard","county":"St. Bernard County","rate":10},"70086":{"city":"Saint James","county":"St. James County","rate":8.5},"70087":{"city":"Saint Rose","county":"St. Charles County","rate":10},"70090":{"city":"Vacherie","county":"St. James County","rate":10.25},"70091":{"city":"Venice","county":"Plaquemines Parish","rate":9.75},"70092":{"city":"Violet","county":"St. Bernard County","rate":10},"70093":{"city":"Belle Chasse","county":"Plaquemines Parish","rate":9.75},"70094":{"city":"Westwego","county":"Jefferson Parish","rate":10.55},"70096":{"city":"Westwego","county":"Jefferson Parish","rate":9.75},"70097":{"city":"Kenner","county":"Jefferson Parish","rate":9.75},"70112":{"city":"New Orleans","county":"Orleans County","rate":10.25},"70113":{"city":"New Orleans","county":"Orleans County","rate":11},"70114":{"city":"New Orleans","county":"Orleans County","rate":10},"70115":{"city":"New Orleans","county":"Orleans County","rate":11},"70116":{"city":"New Orleans","county":"Orleans County","rate":10.25},"70117":{"city":"New Orleans","county":"Orleans County","rate":10},"70118":{"city":"New Orleans","county":"Orleans County","rate":10},"70119":{"city":"New Orleans","county":"Orleans County","rate":10},"70121":{"city":"New Orleans","county":"Jefferson Parish","rate":9.75},"70122":{"city":"New Orleans","county":"Orleans County","rate":10},"70123":{"city":"New Orleans","county":"Jefferson Parish","rate":10.55},"70124":{"city":"New Orleans","county":"Orleans County","rate":10},"70125":{"city":"New Orleans","county":"Orleans County","rate":11},"70126":{"city":"New Orleans","county":"Orleans County","rate":10},"70127":{"city":"New Orleans","county":"Orleans County","rate":10},"70128":{"city":"New Orleans","county":"Orleans County","rate":10},"70129":{"city":"New Orleans","county":"Orleans County","rate":10},"70130":{"city":"New Orleans","county":"Orleans County","rate":12},"70131":{"city":"New Orleans","county":"Orleans County","rate":10},"70139":{"city":"New Orleans","county":"Orleans County","rate":10},"70141":{"city":"New Orleans","county":"Jefferson Parish","rate":10},"70142":{"city":"New Orleans","county":"Orleans County","rate":10},"70143":{"city":"New Orleans","county":"Orleans County","rate":10},"70145":{"city":"New Orleans","county":"Orleans County","rate":10},"70146":{"city":"New Orleans","county":"Orleans County","rate":10},"70148":{"city":"New Orleans","county":"Orleans County","rate":10},"70150":{"city":"New Orleans","county":"Orleans County","rate":10},"70151":{"city":"New Orleans","county":"Orleans County","rate":10},"70152":{"city":"New Orleans","county":"Orleans County","rate":10},"70153":{"city":"New Orleans","county":"Orleans County","rate":10},"70154":{"city":"New Orleans","county":"Orleans County","rate":10},"70156":{"city":"New Orleans","county":"Orleans County","rate":10},"70157":{"city":"New Orleans","county":"Orleans County","rate":10},"70158":{"city":"New Orleans","county":"Orleans County","rate":10},"70159":{"city":"New Orleans","county":"Orleans County","rate":10},"70160":{"city":"New Orleans","county":"Orleans County","rate":10},"70161":{"city":"New Orleans","county":"Orleans County","rate":10},"70162":{"city":"New Orleans","county":"Orleans County","rate":10},"70163":{"city":"New Orleans","county":"Orleans County","rate":10},"70164":{"city":"New Orleans","county":"Orleans County","rate":10},"70165":{"city":"New Orleans","county":"Orleans County","rate":10},"70166":{"city":"New Orleans","county":"Orleans County","rate":10},"70167":{"city":"New Orleans","county":"Orleans County","rate":10},"70170":{"city":"New Orleans","county":"Orleans County","rate":10},"70172":{"city":"New Orleans","county":"Orleans County","rate":10},"70174":{"city":"New Orleans","county":"Orleans County","rate":10},"70175":{"city":"New Orleans","county":"Orleans County","rate":10},"70176":{"city":"New Orleans","county":"Orleans County","rate":10},"70177":{"city":"New Orleans","county":"Orleans County","rate":10},"70178":{"city":"New Orleans","county":"Orleans County","rate":10},"70179":{"city":"New Orleans","county":"Orleans County","rate":10},"70181":{"city":"New Orleans","county":"Jefferson Parish","rate":9.75},"70182":{"city":"New Orleans","county":"Orleans County","rate":10},"70183":{"city":"New Orleans","county":"Jefferson Parish","rate":9.75},"70184":{"city":"New Orleans","county":"Orleans County","rate":10},"70185":{"city":"New Orleans","county":"Orleans County","rate":10},"70186":{"city":"New Orleans","county":"Orleans County","rate":10},"70187":{"city":"New Orleans","county":"Orleans County","rate":10},"70189":{"city":"New Orleans","county":"Orleans County","rate":10},"70190":{"city":"New Orleans","county":"Orleans County","rate":10},"70195":{"city":"New Orleans","county":"Orleans County","rate":10},"70301":{"city":"Thibodaux","county":"Lafourche County","rate":10.5},"70302":{"city":"Thibodaux","county":"Lafourche County","rate":10.35},"70310":{"city":"Thibodaux","county":"Lafourche County","rate":10.35},"70339":{"city":"Pierre Part","county":"Assumption County","rate":10},"70340":{"city":"Amelia","county":"St. Mary County","rate":9.45},"70341":{"city":"Belle Rose","county":"Assumption County","rate":10.25},"70342":{"city":"Berwick","county":"St. Mary County","rate":10.25},"70343":{"city":"Bourg","county":"Terrebonne County","rate":10.5},"70344":{"city":"Chauvin","county":"Terrebonne County","rate":10.5},"70345":{"city":"Cut Off","county":"Lafourche County","rate":10.4},"70346":{"city":"Donaldsonville","county":"Ascension County","rate":11},"70352":{"city":"Donner","county":"Terrebonne County","rate":10.5},"70353":{"city":"Dulac","county":"Terrebonne County","rate":10.5},"70354":{"city":"Galliano","county":"Lafourche County","rate":10.4},"70355":{"city":"Gheens","county":"Lafourche County","rate":9.65},"70356":{"city":"Gibson","county":"Terrebonne County","rate":10.5},"70357":{"city":"Golden Meadow","county":"Lafourche County","rate":10.4},"70358":{"city":"Grand Isle","county":"Jefferson Parish","rate":9.75},"70359":{"city":"Gray","county":"Terrebonne County","rate":10.5},"70360":{"city":"Houma","county":"Terrebonne County","rate":10.5},"70361":{"city":"Houma","county":"Terrebonne County","rate":10.5},"70363":{"city":"Houma","county":"Terrebonne County","rate":10.5},"70364":{"city":"Houma","county":"Terrebonne County","rate":10.5},"70371":{"city":"Kraemer","county":"Lafourche County","rate":9.65},"70372":{"city":"Labadieville","county":"Assumption County","rate":10},"70373":{"city":"Larose","county":"Lafourche County","rate":10.4},"70374":{"city":"Lockport","county":"Lafourche County","rate":10.15},"70375":{"city":"Mathews","county":"Lafourche County","rate":9.65},"70377":{"city":"Montegut","county":"Terrebonne County","rate":10.5},"70380":{"city":"Morgan City","county":"St. Mary County","rate":10.25},"70381":{"city":"Morgan City","county":"St. Mary County","rate":10.25},"70390":{"city":"Napoleonville","county":"Assumption County","rate":10.5},"70391":{"city":"Paincourtville","county":"Assumption County","rate":10},"70392":{"city":"Patterson","county":"St. Mary County","rate":9.45},"70393":{"city":"Plattenville","county":"Assumption County","rate":10},"70394":{"city":"Raceland","county":"Lafourche County","rate":9.65},"70395":{"city":"Schriever","county":"Terrebonne County","rate":10.5},"70397":{"city":"Theriot","county":"Terrebonne County","rate":10.5},"70401":{"city":"Hammond","county":"Tangipahoa County","rate":10.5},"70402":{"city":"Hammond","county":"Tangipahoa County","rate":10.5},"70403":{"city":"Hammond","county":"Tangipahoa County","rate":10.5},"70404":{"city":"Hammond","county":"Tangipahoa County","rate":10.5},"70420":{"city":"Abita Springs","county":"St. Tammany County","rate":9.25},"70421":{"city":"Akers","county":"Tangipahoa County","rate":8.5},"70422":{"city":"Amite","county":"Tangipahoa County","rate":11},"70426":{"city":"Angie","county":"Washington County","rate":10.83},"70427":{"city":"Bogalusa","county":"Washington County","rate":10.83},"70429":{"city":"Bogalusa","county":"Washington County","rate":10.49},"70431":{"city":"Bush","county":"St. Tammany County","rate":10.83},"70433":{"city":"Covington","county":"St. Tammany County","rate":10},"70434":{"city":"Covington","county":"St. Tammany County","rate":9.25},"70435":{"city":"Covington","county":"St. Tammany County","rate":10.83},"70436":{"city":"Fluker","county":"Tangipahoa County","rate":10},"70437":{"city":"Folsom","county":"St. Tammany County","rate":9.75},"70438":{"city":"Franklinton","county":"Washington County","rate":11.5},"70441":{"city":"Greensburg","county":"St. Helena County","rate":11},"70442":{"city":"Husser","county":"Tangipahoa County","rate":8.5},"70443":{"city":"Independence","county":"Tangipahoa County","rate":11},"70444":{"city":"Kentwood","county":"Tangipahoa County","rate":10.83},"70445":{"city":"Lacombe","county":"St. Tammany County","rate":9.25},"70446":{"city":"Loranger","county":"Tangipahoa County","rate":8.5},"70447":{"city":"Madisonville","county":"St. Tammany County","rate":9.25},"70448":{"city":"Mandeville","county":"St. Tammany County","rate":9.75},"70449":{"city":"Maurepas","county":"Livingston County","rate":10},"70450":{"city":"Mount Hermon","county":"Washington County","rate":10.83},"70451":{"city":"Natalbany","county":"Tangipahoa County","rate":8.5},"70452":{"city":"Pearl River","county":"St. Tammany County","rate":9.5},"70453":{"city":"Pine Grove","county":"St. Helena County","rate":10},"70454":{"city":"Ponchatoula","county":"Tangipahoa County","rate":10.5},"70455":{"city":"Robert","county":"Tangipahoa County","rate":8.5},"70456":{"city":"Roseland","county":"Tangipahoa County","rate":11},"70457":{"city":"Saint Benedict","county":"St. Tammany County","rate":9.25},"70458":{"city":"Slidell","county":"St. Tammany County","rate":10.13},"70459":{"city":"Slidell","county":"St. Tammany County","rate":9.63},"70460":{"city":"Slidell","county":"St. Tammany County","rate":9.63},"70461":{"city":"Slidell","county":"St. Tammany County","rate":10.63},"70462":{"city":"Springfield","county":"Livingston County","rate":10.5},"70463":{"city":"Sun","county":"St. Tammany County","rate":9.75},"70464":{"city":"Talisheek","county":"St. Tammany County","rate":9.25},"70465":{"city":"Tangipahoa","county":"Tangipahoa County","rate":10.5},"70466":{"city":"Tickfaw","county":"Tangipahoa County","rate":10.5},"70467":{"city":"Varnado","county":"Washington County","rate":10.83},"70469":{"city":"Slidell","county":"St. Tammany County","rate":9.63},"70470":{"city":"Mandeville","county":"St. Tammany County","rate":9.75},"70471":{"city":"Mandeville","county":"St. Tammany County","rate":9.75},"70501":{"city":"Lafayette","county":"Lafayette County","rate":11},"70502":{"city":"Lafayette","county":"Lafayette County","rate":10},"70503":{"city":"Lafayette","county":"Lafayette County","rate":10},"70504":{"city":"Lafayette","county":"Lafayette County","rate":10},"70505":{"city":"Lafayette","county":"Lafayette County","rate":9},"70506":{"city":"Lafayette","county":"Lafayette County","rate":11},"70507":{"city":"Lafayette","county":"Lafayette County","rate":11},"70508":{"city":"Lafayette","county":"Lafayette County","rate":10},"70509":{"city":"Lafayette","county":"Lafayette County","rate":9},"70510":{"city":"Abbeville","county":"Vermilion County","rate":11},"70511":{"city":"Abbeville","county":"Vermilion County","rate":11},"70512":{"city":"Arnaudville","county":"St. Landry County","rate":10.55},"70513":{"city":"Avery Island","county":"Iberia County","rate":9.25},"70514":{"city":"Baldwin","county":"St. Mary County","rate":10.45},"70515":{"city":"Basile","county":"Evangeline County","rate":11},"70516":{"city":"Branch","county":"Acadia County","rate":9.25},"70517":{"city":"Breaux Bridge","county":"St. Martin County","rate":10.5},"70518":{"city":"Broussard","county":"Lafayette County","rate":11},"70519":{"city":"Cade","county":"St. Martin County","rate":8.5},"70520":{"city":"Carencro","county":"Lafayette County","rate":11},"70521":{"city":"Cecilia","county":"St. Martin County","rate":8.5},"70522":{"city":"Centerville","county":"St. Mary County","rate":9.45},"70523":{"city":"Charenton","county":"St. Mary County","rate":9.45},"70524":{"city":"Chataignier","county":"Evangeline County","rate":11},"70525":{"city":"Church Point","county":"Acadia County","rate":10.55},"70526":{"city":"Crowley","county":"Acadia County","rate":11.25},"70527":{"city":"Crowley","county":"Acadia County","rate":10.5},"70528":{"city":"Delcambre","county":"Vermilion County","rate":11.25},"70529":{"city":"Duson","county":"Lafayette County","rate":11.25},"70531":{"city":"Egan","county":"Acadia County","rate":11.25},"70532":{"city":"Elton","county":"Jefferson Davis County","rate":12},"70533":{"city":"Erath","county":"Vermilion County","rate":11.25},"70534":{"city":"Estherwood","county":"Acadia County","rate":9.25},"70535":{"city":"Eunice","county":"St. Landry County","rate":11},"70537":{"city":"Evangeline","county":"Acadia County","rate":9.25},"70538":{"city":"Franklin","county":"St. Mary County","rate":10.45},"70540":{"city":"Garden City","county":"St. Mary County","rate":9.45},"70541":{"city":"Grand Coteau","county":"St. Landry County","rate":10.55},"70542":{"city":"Gueydan","county":"Vermilion County","rate":9.75},"70543":{"city":"Iota","county":"Acadia County","rate":10.25},"70544":{"city":"Jeanerette","county":"Iberia County","rate":10.45},"70546":{"city":"Jennings","county":"Jefferson Davis County","rate":12},"70548":{"city":"Kaplan","county":"Vermilion County","rate":10.75},"70549":{"city":"Lake Arthur","county":"Jefferson Davis County","rate":11},"70550":{"city":"Lawtell","county":"St. Landry County","rate":10.55},"70551":{"city":"Leonville","county":"St. Landry County","rate":8.55},"70552":{"city":"Loreauville","county":"Iberia County","rate":9.5},"70554":{"city":"Mamou","county":"Evangeline County","rate":11},"70555":{"city":"Maurice","county":"Vermilion County","rate":10.75},"70556":{"city":"Mermentau","county":"Acadia County","rate":9.25},"70558":{"city":"Milton","county":"Lafayette County","rate":9},"70559":{"city":"Morse","county":"Acadia County","rate":9.25},"70560":{"city":"New Iberia","county":"Iberia County","rate":11.25},"70562":{"city":"New Iberia","county":"Iberia County","rate":10.5},"70563":{"city":"New Iberia","county":"Iberia County","rate":11},"70569":{"city":"Lydia","county":"Iberia County","rate":9.25},"70570":{"city":"Opelousas","county":"St. Landry County","rate":12.55},"70571":{"city":"Opelousas","county":"St. Landry County","rate":10.75},"70575":{"city":"Perry","county":"Vermilion County","rate":9.25},"70576":{"city":"Pine Prairie","county":"Evangeline County","rate":11},"70577":{"city":"Port Barre","county":"St. Landry County","rate":10.75},"70578":{"city":"Rayne","county":"Acadia County","rate":11.25},"70580":{"city":"Reddell","county":"Evangeline County","rate":11},"70581":{"city":"Roanoke","county":"Jefferson Davis County","rate":12.5},"70582":{"city":"Saint Martinville","county":"St. Martin County","rate":11},"70583":{"city":"Scott","county":"Lafayette County","rate":11},"70584":{"city":"Sunset","county":"St. Landry County","rate":12.55},"70585":{"city":"Turkey Creek","county":"Evangeline County","rate":11},"70586":{"city":"Ville Platte","county":"Evangeline County","rate":11},"70589":{"city":"Washington","county":"St. Landry County","rate":11},"70591":{"city":"Welsh","county":"Jefferson Davis County","rate":12.5},"70592":{"city":"Youngsville","county":"Lafayette County","rate":10.5},"70593":{"city":"Lafayette","county":"Lafayette County","rate":10},"70596":{"city":"Lafayette","county":"Lafayette County","rate":9},"70598":{"city":"Lafayette","county":"Lafayette County","rate":9},"70601":{"city":"Lake Charles","county":"Calcasieu County","rate":11.75},"70602":{"city":"Lake Charles","county":"Calcasieu County","rate":10.75},"70605":{"city":"Lake Charles","county":"Calcasieu County","rate":11.75},"70606":{"city":"Lake Charles","county":"Calcasieu County","rate":10.75},"70607":{"city":"Lake Charles","county":"Calcasieu County","rate":11.75},"70609":{"city":"Lake Charles","county":"Calcasieu County","rate":10.75},"70611":{"city":"Lake Charles","county":"Calcasieu County","rate":10.75},"70612":{"city":"Lake Charles","county":"Calcasieu County","rate":9.25},"70615":{"city":"Lake Charles","county":"Calcasieu County","rate":10.75},"70616":{"city":"Lake Charles","county":"Calcasieu County","rate":10.75},"70629":{"city":"Lake Charles","county":"Calcasieu County","rate":10.75},"70630":{"city":"Bell City","county":"Calcasieu County","rate":10.75},"70631":{"city":"Cameron","county":"Cameron County","rate":5},"70632":{"city":"Creole","county":"Cameron County","rate":5},"70633":{"city":"Dequincy","county":"Calcasieu County","rate":10.75},"70634":{"city":"Deridder","county":"Beauregard County","rate":11.25},"70637":{"city":"Dry Creek","county":"Beauregard County","rate":9.7},"70638":{"city":"Elizabeth","county":"Allen County","rate":11},"70639":{"city":"Evans","county":"Vernon County","rate":9},"70640":{"city":"Fenton","county":"Jefferson Davis County","rate":10.5},"70643":{"city":"Grand Chenier","county":"Cameron County","rate":5},"70644":{"city":"Grant","county":"Allen County","rate":9.7},"70645":{"city":"Hackberry","county":"Cameron County","rate":5},"70646":{"city":"Hayes","county":"Calcasieu County","rate":10.75},"70647":{"city":"Iowa","county":"Calcasieu County","rate":19.5},"70648":{"city":"Kinder","county":"Allen County","rate":12},"70650":{"city":"Lacassine","county":"Jefferson Davis County","rate":10.5},"70651":{"city":"Leblanc","county":"Allen County","rate":9.7},"70652":{"city":"Longville","county":"Beauregard County","rate":8.75},"70653":{"city":"Merryville","county":"Beauregard County","rate":10},"70654":{"city":"Mittie","county":"Allen County","rate":9.7},"70655":{"city":"Oberlin","county":"Allen County","rate":11},"70656":{"city":"Pitkin","county":"Vernon County","rate":9.7},"70657":{"city":"Ragley","county":"Beauregard County","rate":10.5},"70658":{"city":"Reeves","county":"Allen County","rate":10.7},"70659":{"city":"Rosepine","county":"Vernon County","rate":10.5},"70660":{"city":"Singer","county":"Beauregard County","rate":10.75},"70661":{"city":"Starks","county":"Calcasieu County","rate":10.75},"70662":{"city":"Sugartown","county":"Beauregard County","rate":9.7},"70663":{"city":"Sulphur","county":"Calcasieu County","rate":12.75},"70664":{"city":"Sulphur","county":"Calcasieu County","rate":10.75},"70665":{"city":"Sulphur","county":"Calcasieu County","rate":12.75},"70668":{"city":"Vinton","county":"Calcasieu County","rate":17.75},"70669":{"city":"Westlake","county":"Calcasieu County","rate":12.75},"70704":{"city":"Baker","county":"East Baton Rouge Parish","rate":11},"70706":{"city":"Denham Springs","county":"Livingston County","rate":10.5},"70707":{"city":"Gonzales","county":"Ascension County","rate":9.5},"70710":{"city":"Addis","county":"West Baton Rouge County","rate":10.25},"70711":{"city":"Albany","county":"Livingston County","rate":10.5},"70712":{"city":"Angola","county":"West Feliciana County","rate":10},"70714":{"city":"Baker","county":"East Baton Rouge Parish","rate":11},"70715":{"city":"Batchelor","county":"Pointe Coupee County","rate":9.25},"70718":{"city":"Brittany","county":"Ascension County","rate":9.5},"70719":{"city":"Brusly","county":"West Baton Rouge County","rate":10.25},"70721":{"city":"Carville","county":"Iberville County","rate":10.92},"70722":{"city":"Clinton","county":"East Feliciana County","rate":10.5},"70723":{"city":"Convent","county":"St. James County","rate":8.5},"70725":{"city":"Darrow","county":"Ascension County","rate":9.5},"70726":{"city":"Denham Springs","county":"Livingston County","rate":11.5},"70727":{"city":"Denham Springs","county":"Livingston County","rate":10.5},"70728":{"city":"Duplessis","county":"Ascension County","rate":9.5},"70729":{"city":"Erwinville","county":"West Baton Rouge County","rate":10.25},"70730":{"city":"Ethel","county":"East Feliciana County","rate":10},"70732":{"city":"Fordoche","county":"Pointe Coupee County","rate":10.25},"70733":{"city":"French Settlement","county":"Livingston County","rate":9},"70734":{"city":"Geismar","county":"Ascension County","rate":9.5},"70736":{"city":"Glynn","county":"Pointe Coupee County","rate":10.25},"70737":{"city":"Gonzales","county":"Ascension County","rate":10.5},"70738":{"city":"Burnside","county":"Ascension County","rate":9.5},"70739":{"city":"Greenwell Springs","county":"East Baton Rouge Parish","rate":11},"70740":{"city":"Grosse Tete","county":"Iberville County","rate":10.25},"70743":{"city":"Hester","county":"St. James County","rate":8.5},"70744":{"city":"Holden","county":"Livingston County","rate":11},"70747":{"city":"Innis","county":"Pointe Coupee County","rate":9.25},"70748":{"city":"Jackson","county":"East Feliciana County","rate":10.5},"70749":{"city":"Jarreau","county":"Pointe Coupee County","rate":9.25},"70750":{"city":"Krotz Springs","county":"St. Landry County","rate":10.55},"70752":{"city":"Lakeland","county":"Pointe Coupee County","rate":9.25},"70753":{"city":"Lettsworth","county":"Pointe Coupee County","rate":10},"70754":{"city":"Livingston","county":"Livingston County","rate":10},"70755":{"city":"Livonia","county":"Pointe Coupee County","rate":10.25},"70756":{"city":"Lottie","county":"Pointe Coupee County","rate":10.25},"70757":{"city":"Maringouin","county":"Iberville County","rate":10.25},"70759":{"city":"Morganza","county":"Pointe Coupee County","rate":10.25},"70760":{"city":"New Roads","county":"Pointe Coupee County","rate":10.25},"70761":{"city":"Norwood","county":"East Feliciana County","rate":10},"70762":{"city":"Oscar","county":"Pointe Coupee County","rate":9.25},"70763":{"city":"Paulina","county":"St. James County","rate":9.5},"70764":{"city":"Plaquemine","county":"Iberville County","rate":10.25},"70765":{"city":"Plaquemine","county":"Iberville County","rate":10.25},"70767":{"city":"Port Allen","county":"West Baton Rouge County","rate":10.75},"70769":{"city":"Prairieville","county":"Ascension County","rate":10.25},"70770":{"city":"Pride","county":"East Baton Rouge Parish","rate":11},"70772":{"city":"Rosedale","county":"Iberville County","rate":10.25},"70773":{"city":"Rougon","county":"Pointe Coupee County","rate":9.25},"70774":{"city":"Saint Amant","county":"Ascension County","rate":9.5},"70775":{"city":"Saint Francisville","county":"West Feliciana County","rate":10.5},"70776":{"city":"Saint Gabriel","county":"Iberville County","rate":10.92},"70777":{"city":"Slaughter","county":"East Feliciana County","rate":11},"70778":{"city":"Sorrento","county":"Ascension County","rate":9.5},"70780":{"city":"Sunshine","county":"Iberville County","rate":10.92},"70782":{"city":"Tunica","county":"West Feliciana County","rate":10},"70783":{"city":"Ventress","county":"Pointe Coupee County","rate":9.25},"70784":{"city":"Wakefield","county":"West Feliciana County","rate":10},"70785":{"city":"Walker","county":"Livingston County","rate":11},"70786":{"city":"Watson","county":"Livingston County","rate":10.5},"70787":{"city":"Weyanoke","county":"West Feliciana County","rate":10},"70788":{"city":"White Castle","county":"Iberville County","rate":10.25},"70789":{"city":"Wilson","county":"East Feliciana County","rate":10},"70791":{"city":"Zachary","county":"East Baton Rouge Parish","rate":11.5},"70792":{"city":"Uncle Sam","county":"St. James County","rate":8.5},"70801":{"city":"Baton Rouge","county":"East Baton Rouge Parish","rate":12.5},"70802":{"city":"Baton Rouge","county":"East Baton Rouge Parish","rate":12.5},"70803":{"city":"Baton Rouge","county":"East Baton Rouge Parish","rate":11.5},"70804":{"city":"Baton Rouge","county":"East Baton Rouge Parish","rate":10.5},"70805":{"city":"Baton Rouge","county":"East Baton Rouge Parish","rate":11.5},"70806":{"city":"Baton Rouge","county":"East Baton Rouge Parish","rate":10.5},"70807":{"city":"Baton Rouge","county":"East Baton Rouge Parish","rate":11.5},"70808":{"city":"Baton Rouge","county":"East Baton Rouge Parish","rate":12.5},"70809":{"city":"Baton Rouge","county":"East Baton Rouge Parish","rate":10.5},"70810":{"city":"Baton Rouge","county":"East Baton Rouge Parish","rate":12.5},"70811":{"city":"Baton Rouge","county":"East Baton Rouge Parish","rate":11},"70812":{"city":"Baton Rouge","county":"East Baton Rouge Parish","rate":10.5},"70813":{"city":"Baton Rouge","county":"East Baton Rouge Parish","rate":11.5},"70814":{"city":"Baton Rouge","county":"East Baton Rouge Parish","rate":10.5},"70815":{"city":"Baton Rouge","county":"East Baton Rouge Parish","rate":10.5},"70816":{"city":"Baton Rouge","county":"East Baton Rouge Parish","rate":10.5},"70817":{"city":"Baton Rouge","county":"East Baton Rouge Parish","rate":10.5},"70818":{"city":"Baton Rouge","county":"East Baton Rouge Parish","rate":11},"70819":{"city":"Baton Rouge","county":"East Baton Rouge Parish","rate":10.5},"70820":{"city":"Baton Rouge","county":"East Baton Rouge Parish","rate":12.5},"70821":{"city":"Baton Rouge","county":"East Baton Rouge Parish","rate":10.5},"70822":{"city":"Baton Rouge","county":"East Baton Rouge Parish","rate":10.5},"70823":{"city":"Baton Rouge","county":"East Baton Rouge Parish","rate":10.5},"70825":{"city":"Baton Rouge","county":"East Baton Rouge Parish","rate":10.5},"70826":{"city":"Baton Rouge","county":"East Baton Rouge Parish","rate":10.5},"70827":{"city":"Baton Rouge","county":"East Baton Rouge Parish","rate":10.5},"70831":{"city":"Baton Rouge","county":"East Baton Rouge Parish","rate":10.5},"70833":{"city":"Baton Rouge","county":"East Baton Rouge Parish","rate":10.5},"70835":{"city":"Baton Rouge","county":"East Baton Rouge Parish","rate":10.5},"70836":{"city":"Baton Rouge","county":"East Baton Rouge Parish","rate":10.5},"70837":{"city":"Baton Rouge","county":"East Baton Rouge Parish","rate":10.5},"70873":{"city":"Baton Rouge","county":"East Baton Rouge Parish","rate":10.5},"70874":{"city":"Baton Rouge","county":"East Baton Rouge Parish","rate":10.5},"70879":{"city":"Baton Rouge","county":"East Baton Rouge Parish","rate":10.5},"70884":{"city":"Baton Rouge","county":"East Baton Rouge Parish","rate":10.5},"70891":{"city":"Baton Rouge","county":"East Baton Rouge Parish","rate":10.5},"70892":{"city":"Baton Rouge","county":"East Baton Rouge Parish","rate":10.5},"70893":{"city":"Baton Rouge","county":"East Baton Rouge Parish","rate":11.5},"70894":{"city":"Baton Rouge","county":"East Baton Rouge Parish","rate":10.5},"70895":{"city":"Baton Rouge","county":"East Baton Rouge Parish","rate":10.5},"70896":{"city":"Baton Rouge","county":"East Baton Rouge Parish","rate":10.5},"70898":{"city":"Baton Rouge","county":"East Baton Rouge Parish","rate":10.5},"71001":{"city":"Arcadia","county":"Bienville County","rate":10.5},"71002":{"city":"Ashland","county":"Natchitoches County","rate":9},"71003":{"city":"Athens","county":"Claiborne County","rate":9.63},"71004":{"city":"Belcher","county":"Caddo Parish","rate":9.35},"71006":{"city":"Benton","county":"Bossier County","rate":10.25},"71007":{"city":"Bethany","county":"Caddo Parish","rate":9.35},"71008":{"city":"Bienville","county":"Bienville County","rate":8},"71009":{"city":"Blanchard","county":"Caddo Parish","rate":10.35},"71016":{"city":"Castor","county":"Bienville County","rate":9},"71018":{"city":"Cotton Valley","county":"Webster County","rate":9.25},"71019":{"city":"Coushatta","county":"Red River County","rate":10.5},"71021":{"city":"Cullen","county":"Webster County","rate":10.5},"71023":{"city":"Doyline","county":"Webster County","rate":9.25},"71024":{"city":"Dubberly","county":"Webster County","rate":8.5},"71027":{"city":"Frierson","county":"De Soto County","rate":9},"71028":{"city":"Gibsland","county":"Bienville County","rate":10},"71029":{"city":"Gilliam","county":"Caddo Parish","rate":9.35},"71030":{"city":"Gloster","county":"De Soto County","rate":9},"71031":{"city":"Goldonna","county":"Natchitoches County","rate":10},"71032":{"city":"Grand Cane","county":"De Soto County","rate":10.25},"71033":{"city":"Greenwood","county":"Caddo Parish","rate":10.35},"71034":{"city":"Hall Summit","county":"Red River County","rate":10.5},"71037":{"city":"Haughton","county":"Bossier County","rate":10.25},"71038":{"city":"Haynesville","county":"Claiborne County","rate":10.13},"71039":{"city":"Heflin","county":"Webster County","rate":8},"71040":{"city":"Homer","county":"Claiborne County","rate":11},"71043":{"city":"Hosston","county":"Caddo Parish","rate":10.35},"71044":{"city":"Ida","county":"Caddo Parish","rate":11.35},"71045":{"city":"Jamestown","county":"Bienville County","rate":8},"71046":{"city":"Keatchie","county":"De Soto County","rate":10},"71047":{"city":"Keithville","county":"Caddo Parish","rate":10},"71048":{"city":"Lisbon","county":"Claiborne County","rate":8.62},"71049":{"city":"Logansport","county":"De Soto County","rate":10},"71050":{"city":"Longstreet","county":"De Soto County","rate":9},"71051":{"city":"Elm Grove","county":"Bossier County","rate":9.25},"71052":{"city":"Mansfield","county":"De Soto County","rate":10.5},"71055":{"city":"Minden","county":"Webster County","rate":12.5},"71058":{"city":"Minden","county":"Webster County","rate":12.5},"71060":{"city":"Mooringsport","county":"Caddo Parish","rate":10.35},"71061":{"city":"Oil City","county":"Caddo Parish","rate":10.35},"71063":{"city":"Pelican","county":"De Soto County","rate":9.63},"71064":{"city":"Plain Dealing","county":"Bossier County","rate":10.25},"71065":{"city":"Pleasant Hill","county":"Sabine County","rate":10.63},"71066":{"city":"Powhatan","county":"Natchitoches County","rate":10},"71067":{"city":"Princeton","county":"Bossier County","rate":9.25},"71068":{"city":"Ringgold","county":"Bienville County","rate":10},"71069":{"city":"Rodessa","county":"Caddo Parish","rate":10.35},"71070":{"city":"Saline","county":"Bienville County","rate":10},"71071":{"city":"Sarepta","county":"Webster County","rate":10.5},"71072":{"city":"Shongaloo","county":"Webster County","rate":8.62},"71073":{"city":"Sibley","county":"Webster County","rate":10.5},"71075":{"city":"Springhill","county":"Webster County","rate":10.5},"71078":{"city":"Stonewall","county":"De Soto County","rate":10},"71079":{"city":"Summerfield","county":"Claiborne County","rate":8.62},"71080":{"city":"Taylor","county":"Bienville County","rate":8},"71082":{"city":"Vivian","county":"Caddo Parish","rate":10.35},"71101":{"city":"Shreveport","county":"Caddo Parish","rate":10.25},"71102":{"city":"Shreveport","county":"Caddo Parish","rate":9.6},"71103":{"city":"Shreveport","county":"Caddo Parish","rate":9.6},"71104":{"city":"Shreveport","county":"Caddo Parish","rate":10.6},"71105":{"city":"Shreveport","county":"Caddo Parish","rate":10.25},"71106":{"city":"Shreveport","county":"Caddo Parish","rate":9.6},"71107":{"city":"Shreveport","county":"Caddo Parish","rate":10.35},"71108":{"city":"Shreveport","county":"Caddo Parish","rate":9.6},"71109":{"city":"Shreveport","county":"Caddo Parish","rate":9.6},"71110":{"city":"Barksdale Afb","county":"Bossier County","rate":10},"71111":{"city":"Bossier City","county":"Bossier County","rate":10},"71112":{"city":"Bossier City","county":"Bossier County","rate":10},"71113":{"city":"Bossier City","county":"Bossier County","rate":10},"71115":{"city":"Shreveport","county":"Caddo Parish","rate":9.6},"71118":{"city":"Shreveport","county":"Caddo Parish","rate":9.6},"71119":{"city":"Shreveport","county":"Caddo Parish","rate":10.35},"71120":{"city":"Shreveport","county":"Caddo Parish","rate":9.6},"71129":{"city":"Shreveport","county":"Caddo Parish","rate":10.35},"71130":{"city":"Shreveport","county":"Caddo Parish","rate":9.6},"71133":{"city":"Shreveport","county":"Caddo Parish","rate":9.6},"71134":{"city":"Shreveport","county":"Caddo Parish","rate":9.6},"71135":{"city":"Shreveport","county":"Caddo Parish","rate":9.6},"71136":{"city":"Shreveport","county":"Caddo Parish","rate":9.6},"71137":{"city":"Shreveport","county":"Caddo Parish","rate":10.25},"71138":{"city":"Shreveport","county":"Caddo Parish","rate":9.6},"71148":{"city":"Shreveport","county":"Caddo Parish","rate":9.6},"71149":{"city":"Shreveport","county":"Caddo Parish","rate":9.6},"71150":{"city":"Shreveport","county":"Caddo Parish","rate":9.6},"71151":{"city":"Shreveport","county":"Caddo Parish","rate":9.6},"71152":{"city":"Shreveport","county":"Caddo Parish","rate":9.6},"71153":{"city":"Shreveport","county":"Caddo Parish","rate":9.6},"71154":{"city":"Shreveport","county":"Caddo Parish","rate":9.6},"71156":{"city":"Shreveport","county":"Caddo Parish","rate":9.6},"71161":{"city":"Shreveport","county":"Caddo Parish","rate":9.6},"71162":{"city":"Shreveport","county":"Caddo Parish","rate":9.6},"71163":{"city":"Shreveport","county":"Caddo Parish","rate":9.6},"71164":{"city":"Shreveport","county":"Caddo Parish","rate":9.6},"71165":{"city":"Shreveport","county":"Caddo Parish","rate":9.6},"71166":{"city":"Shreveport","county":"Caddo Parish","rate":9.6},"71171":{"city":"Bossier City","county":"Bossier County","rate":10},"71172":{"city":"Bossier City","county":"Bossier County","rate":10},"71201":{"city":"Monroe","county":"Ouachita Parish","rate":12.99},"71202":{"city":"Monroe","county":"Ouachita Parish","rate":10.99},"71203":{"city":"Monroe","county":"Ouachita Parish","rate":13.5},"71207":{"city":"Monroe","county":"Ouachita Parish","rate":10.99},"71209":{"city":"Monroe","county":"Ouachita Parish","rate":10.99},"71210":{"city":"Monroe","county":"Ouachita Parish","rate":10.99},"71211":{"city":"Monroe","county":"Ouachita Parish","rate":10.99},"71212":{"city":"Monroe","county":"Ouachita Parish","rate":10.99},"71213":{"city":"Monroe","county":"Ouachita Parish","rate":10.99},"71217":{"city":"Monroe","county":"Ouachita Parish","rate":10.99},"71218":{"city":"Archibald","county":"Richland County","rate":9.25},"71219":{"city":"Baskin","county":"Franklin County","rate":10},"71220":{"city":"Bastrop","county":"Morehouse County","rate":11},"71221":{"city":"Bastrop","county":"Morehouse County","rate":11},"71222":{"city":"Bernice","county":"Union County","rate":12},"71223":{"city":"Bonita","county":"Morehouse County","rate":11},"71225":{"city":"Calhoun","county":"Ouachita Parish","rate":10.99},"71226":{"city":"Chatham","county":"Jackson County","rate":10},"71227":{"city":"Choudrant","county":"Lincoln County","rate":10.99},"71229":{"city":"Collinston","county":"Morehouse County","rate":10.99},"71230":{"city":"Crowville","county":"Franklin County","rate":9},"71232":{"city":"Delhi","county":"Richland County","rate":11.25},"71233":{"city":"Delta","county":"Madison County","rate":9.5},"71234":{"city":"Downsville","county":"Union County","rate":10.99},"71235":{"city":"Dubach","county":"Lincoln County","rate":10},"71237":{"city":"Epps","county":"West Carroll County","rate":11},"71238":{"city":"Eros","county":"Jackson County","rate":10.99},"71240":{"city":"Fairbanks","county":"Ouachita Parish","rate":10.99},"71241":{"city":"Farmerville","county":"Union County","rate":12},"71242":{"city":"Forest","county":"West Carroll County","rate":11},"71243":{"city":"Fort Necessity","county":"Franklin County","rate":9},"71245":{"city":"Grambling","county":"Lincoln County","rate":11.5},"71247":{"city":"Hodge","county":"Jackson County","rate":10},"71249":{"city":"Jigger","county":"Franklin County","rate":9},"71250":{"city":"Jones","county":"Morehouse County","rate":9},"71251":{"city":"Jonesboro","county":"Jackson County","rate":10},"71253":{"city":"Kilbourne","county":"West Carroll County","rate":11},"71254":{"city":"Lake Providence","county":"East Carroll County","rate":12},"71256":{"city":"Lillie","county":"Union County","rate":11},"71259":{"city":"Mangham","county":"Richland County","rate":10.25},"71260":{"city":"Marion","county":"Union County","rate":11},"71261":{"city":"Mer Rouge","county":"Morehouse County","rate":11},"71263":{"city":"Oak Grove","county":"West Carroll County","rate":11.5},"71264":{"city":"Oak Ridge","county":"Morehouse County","rate":9.25},"71266":{"city":"Pioneer","county":"West Carroll County","rate":11},"71268":{"city":"Quitman","county":"Jackson County","rate":10},"71269":{"city":"Rayville","county":"Richland County","rate":10.75},"71270":{"city":"Ruston","county":"Lincoln County","rate":12.75},"71272":{"city":"Ruston","county":"Lincoln County","rate":11},"71273":{"city":"Ruston","county":"Lincoln County","rate":11},"71275":{"city":"Simsboro","county":"Lincoln County","rate":10},"71276":{"city":"Sondheimer","county":"East Carroll County","rate":10},"71277":{"city":"Spearsville","county":"Union County","rate":10},"71279":{"city":"Start","county":"Richland County","rate":9.25},"71280":{"city":"Sterlington","county":"Ouachita Parish","rate":13.5},"71281":{"city":"Swartz","county":"Ouachita Parish","rate":10.99},"71282":{"city":"Tallulah","county":"Madison County","rate":11},"71284":{"city":"Tallulah","county":"Madison County","rate":11},"71286":{"city":"Transylvania","county":"East Carroll County","rate":10},"71291":{"city":"West Monroe","county":"Ouachita Parish","rate":11.99},"71292":{"city":"West Monroe","county":"Ouachita Parish","rate":11.99},"71294":{"city":"West Monroe","county":"Ouachita Parish","rate":10.99},"71295":{"city":"Winnsboro","county":"Franklin County","rate":11},"71301":{"city":"Alexandria","county":"Rapides County","rate":10.5},"71302":{"city":"Alexandria","county":"Rapides County","rate":10.5},"71303":{"city":"Alexandria","county":"Rapides County","rate":10.5},"71306":{"city":"Alexandria","county":"Rapides County","rate":10.5},"71307":{"city":"Alexandria","county":"Rapides County","rate":10.5},"71309":{"city":"Alexandria","county":"Rapides County","rate":10.5},"71315":{"city":"Alexandria","county":"Rapides County","rate":10.5},"71316":{"city":"Acme","county":"Concordia County","rate":9.75},"71320":{"city":"Bordelonville","county":"Avoyelles County","rate":8.25},"71322":{"city":"Bunkie","county":"Avoyelles County","rate":10.55},"71323":{"city":"Center Point","county":"Avoyelles County","rate":9.5},"71324":{"city":"Chase","county":"Franklin County","rate":9},"71325":{"city":"Cheneyville","county":"Rapides County","rate":11},"71326":{"city":"Clayton","county":"Concordia County","rate":11},"71327":{"city":"Cottonport","county":"Avoyelles County","rate":10.25},"71328":{"city":"Deville","county":"Rapides County","rate":9.5},"71329":{"city":"Dupont","county":"Avoyelles County","rate":8.25},"71330":{"city":"Echo","county":"Rapides County","rate":8.5},"71331":{"city":"Effie","county":"Avoyelles County","rate":8.25},"71333":{"city":"Evergreen","county":"Avoyelles County","rate":8.25},"71334":{"city":"Ferriday","county":"Concordia County","rate":10.75},"71336":{"city":"Gilbert","county":"Franklin County","rate":10},"71339":{"city":"Hamburg","county":"Avoyelles County","rate":8.25},"71340":{"city":"Harrisonburg","county":"Catahoula County","rate":11},"71341":{"city":"Hessmer","county":"Avoyelles County","rate":9.25},"71342":{"city":"Jena","county":"La Salle County","rate":9},"71343":{"city":"Jonesville","county":"Catahoula County","rate":12},"71345":{"city":"Lebeau","county":"St. Landry County","rate":10.55},"71346":{"city":"Lecompte","county":"Rapides County","rate":10.5},"71348":{"city":"Libuse","county":"Rapides County","rate":9.5},"71350":{"city":"Mansura","county":"Avoyelles County","rate":10.25},"71351":{"city":"Marksville","county":"Avoyelles County","rate":11},"71353":{"city":"Melville","county":"St. Landry County","rate":10.75},"71354":{"city":"Monterey","county":"Concordia County","rate":11},"71355":{"city":"Moreauville","county":"Avoyelles County","rate":9.75},"71356":{"city":"Morrow","county":"St. Landry County","rate":10.55},"71357":{"city":"Newellton","county":"Tensas County","rate":11.5},"71358":{"city":"Palmetto","county":"St. Landry County","rate":10.55},"71359":{"city":"Pineville","county":"Rapides County","rate":10.5},"71360":{"city":"Pineville","county":"Rapides County","rate":10.5},"71361":{"city":"Pineville","county":"Rapides County","rate":10.5},"71362":{"city":"Plaucheville","county":"Avoyelles County","rate":10.55},"71363":{"city":"Rhinehart","county":"Catahoula County","rate":11},"71365":{"city":"Ruby","county":"Rapides County","rate":9.5},"71366":{"city":"Saint Joseph","county":"Tensas County","rate":11.75},"71367":{"city":"Saint Landry","county":"Evangeline County","rate":11},"71368":{"city":"Sicily Island","county":"Catahoula County","rate":11},"71369":{"city":"Simmesport","county":"Avoyelles County","rate":10.25},"71371":{"city":"Trout","county":"La Salle County","rate":8},"71373":{"city":"Vidalia","county":"Concordia County","rate":9.75},"71375":{"city":"Waterproof","county":"Tensas County","rate":11.5},"71377":{"city":"Wildsville","county":"Concordia County","rate":9.75},"71378":{"city":"Wisner","county":"Franklin County","rate":11},"71401":{"city":"Aimwell","county":"Catahoula County","rate":11},"71403":{"city":"Anacoco","county":"Vernon County","rate":9.63},"71404":{"city":"Atlanta","county":"Winn County","rate":9},"71405":{"city":"Ball","county":"Rapides County","rate":10.5},"71406":{"city":"Belmont","county":"Sabine County","rate":9.63},"71407":{"city":"Bentley","county":"Grant County","rate":10},"71409":{"city":"Boyce","county":"Rapides County","rate":11},"71410":{"city":"Calvin","county":"Winn County","rate":9},"71411":{"city":"Campti","county":"Natchitoches County","rate":10.5},"71414":{"city":"Clarence","county":"Natchitoches County","rate":10},"71415":{"city":"Clarks","county":"Caldwell County","rate":10},"71416":{"city":"Cloutierville","county":"Natchitoches County","rate":10},"71417":{"city":"Colfax","county":"Grant County","rate":11},"71418":{"city":"Columbia","county":"Caldwell County","rate":11},"71419":{"city":"Converse","county":"Sabine County","rate":10.63},"71422":{"city":"Dodson","county":"Winn County","rate":10},"71423":{"city":"Dry Prong","county":"Grant County","rate":11},"71424":{"city":"Elmer","county":"Rapides County","rate":8.5},"71425":{"city":"Enterprise","county":"Catahoula County","rate":11},"71426":{"city":"Fisher","county":"Sabine County","rate":9.63},"71427":{"city":"Flatwoods","county":"Rapides County","rate":9},"71428":{"city":"Flora","county":"Natchitoches County","rate":9},"71429":{"city":"Florien","county":"Sabine County","rate":10.63},"71430":{"city":"Forest Hill","county":"Rapides County","rate":9.5},"71431":{"city":"Gardner","county":"Rapides County","rate":8.5},"71432":{"city":"Georgetown","county":"Grant County","rate":11},"71433":{"city":"Glenmora","county":"Rapides County","rate":10},"71434":{"city":"Gorum","county":"Natchitoches County","rate":9},"71435":{"city":"Grayson","county":"Caldwell County","rate":11},"71438":{"city":"Hineston","county":"Rapides County","rate":9},"71439":{"city":"Hornbeck","county":"Vernon County","rate":10},"71440":{"city":"Joyce","county":"Winn County","rate":9},"71441":{"city":"Kelly","county":"Caldwell County","rate":10},"71443":{"city":"Kurthwood","county":"Vernon County","rate":10.5},"71446":{"city":"Leesville","county":"Vernon County","rate":10.5},"71447":{"city":"Lena","county":"Rapides County","rate":9},"71448":{"city":"Longleaf","county":"Rapides County","rate":9.5},"71449":{"city":"Many","county":"Sabine County","rate":10.63},"71450":{"city":"Marthaville","county":"Natchitoches County","rate":9.63},"71452":{"city":"Melrose","county":"Natchitoches County","rate":10},"71454":{"city":"Montgomery","county":"Grant County","rate":10},"71455":{"city":"Mora","county":"Natchitoches County","rate":9},"71456":{"city":"Natchez","county":"Natchitoches County","rate":10},"71457":{"city":"Natchitoches","county":"Natchitoches County","rate":12.5},"71458":{"city":"Natchitoches","county":"Natchitoches County","rate":11.5},"71459":{"city":"Fort Polk","county":"Vernon County","rate":9},"71460":{"city":"Negreet","county":"Sabine County","rate":9.63},"71461":{"city":"New Llano","county":"Vernon County","rate":10.5},"71462":{"city":"Noble","county":"Sabine County","rate":9.63},"71463":{"city":"Oakdale","county":"Allen County","rate":11},"71465":{"city":"Olla","county":"La Salle County","rate":11},"71466":{"city":"Otis","county":"Rapides County","rate":8.5},"71467":{"city":"Pollock","county":"Grant County","rate":10.5},"71468":{"city":"Provencal","county":"Natchitoches County","rate":9.63},"71469":{"city":"Robeline","county":"Natchitoches County","rate":10.5},"71471":{"city":"Saint Maurice","county":"Winn County","rate":9},"71472":{"city":"Sieper","county":"Rapides County","rate":9},"71473":{"city":"Sikes","county":"Winn County","rate":9},"71474":{"city":"Simpson","county":"Vernon County","rate":9},"71475":{"city":"Slagle","county":"Vernon County","rate":9},"71477":{"city":"Tioga","county":"Rapides County","rate":8.5},"71479":{"city":"Tullos","county":"La Salle County","rate":9.5},"71480":{"city":"Urania","county":"La Salle County","rate":8},"71483":{"city":"Winnfield","county":"Winn County","rate":10.5},"71485":{"city":"Woodworth","county":"Rapides County","rate":10.5},"71486":{"city":"Zwolle","county":"Sabine County","rate":11.63},"71496":{"city":"Leesville","county":"Vernon County","rate":10.5},"71497":{"city":"Natchitoches","county":"Natchitoches County","rate":10.5}}}